secretfinder/__init__.py
secretfinder/providers.py
secretfinder-0.2.1.dist-info/LICENSE
secretfinder-0.2.1.dist-info/METADATA
secretfinder-0.2.1.dist-info/WHEEL
secretfinder-0.2.1.dist-info/top_level.txt
secretfinder-0.2.1.dist-info/RECORD
