Metadata-Version: 2.1
Name: secretfinder
Version: 0.2.1
Summary: Get your hard won secrets, simply
Home-page: https://github.com/buddylindsey/secret-finder
Author: Buddy Lindsey
License: UNKNOWN
Project-URL: Documentation, https://github.com/buddylindsey/secret-finder
Project-URL: Source, https://github.com/buddylindsey/secret-finder
Platform: UNKNOWN
Classifier: Development Status :: 3 - Alpha
Classifier: Intended Audience :: Developers
Classifier: Natural Language :: English
Classifier: License :: OSI Approved :: MIT License
Classifier: Programming Language :: Python
Classifier: Programming Language :: Python :: 3
Classifier: Programming Language :: Python :: 3.7
Classifier: Programming Language :: Python :: 3.8
Requires-Python: >=3.7
Requires-Dist: boto3 (<1.11,>=1.10.29)
